Hiram_sdk_the_one/__init__.py
Hiram_sdk_the_one/functions.py
Hiram_sdk_lotr-0.0.1.dist-info/METADATA
Hiram_sdk_lotr-0.0.1.dist-info/WHEEL
Hiram_sdk_lotr-0.0.1.dist-info/top_level.txt
Hiram_sdk_lotr-0.0.1.dist-info/RECORD
