Metadata-Version: 2.1
Name: Hiram-sdk-lotr
Version: 0.0.1
Summary: SDK package for The One Api 
Author: Harios
Author-email: hiramrios26@gmail.com
Classifier: Development Status :: 1 - Planning
Classifier: Intended Audience :: Developers
Classifier: Programming Language :: Python :: 3
Classifier: Operating System :: Unix
Classifier: Operating System :: MacOS :: MacOS X
Classifier: Operating System :: Microsoft :: Windows
